{"organizations": [], "uuid": "d1abc1b7f0654f81e1247e4daf401e5861f50a0e", "thread": {"social": {"gplus": {"shares": 1}, "pinterest": {"shares": 0}, "vk": {"shares": 0}, "linkedin": {"shares": 0}, "facebook": {"likes": 231, "shares": 231, "comments": 0}, "stumbledupon": {"shares": 0}}, "site_full": "www.7sur7.be", "main_image": "http://static2.7sur7.be/static/photo/2016/8/16/6/20161002072039/media_xll_9121281.jpg", "site_section": "http://www.7s7.be/rss.xml", "section_title": "7SUR7.be Info, sport et showbiz, 24/24, 7/7, plus de 350 mises à jour quotidiennes", "url": "http://www.7sur7.be/7s7/fr/1505/Monde/article/detail/2893249/2016/10/02/Plus-de-70-blesses-suite-a-une-explosion-dans-un-cafe-pres-de-Malaga.dhtml", "country": "BE", "domain_rank": 8663, "title": "Plus de 70 blessés suite à une explosion dans un café près de Malaga", "performance_score": 2, "site": "7sur7.be", "participants_count": 1, "title_full": "Plus de 70 blessés suite à une explosion dans un café près de Malaga", "spam_score": 0.0, "site_type": "news", "published": "2016-10-02T13:32:00.000+03:00", "replies_count": 0, "uuid": "d1abc1b7f0654f81e1247e4daf401e5861f50a0e"}, "author": "rédaction", "url": "http://www.7sur7.be/7s7/fr/1505/Monde/article/detail/2893249/2016/10/02/Plus-de-70-blesses-suite-a-une-explosion-dans-un-cafe-pres-de-Malaga.dhtml", "ord_in_thread": 0, "title": "Plus de 70 blessés suite à une explosion dans un café près de Malaga", "locations": [], "entities": {"persons": [], "locations": [], "organizations": []}, "highlightText": "", "language": "french", "persons": [], "text": "2/10/16 - 07h32 Source: Belga © reuters. vidéo Une septantaine de personnes ont été blessées à Velez-Malaga (Andalousie), situé à proximité de Malaga, à la suite d'une explosion au gaz dans un café, rapportent les médias espagnols. © reuters. \nSelon le journal La Opinión, une bombonne de gaz a explosé dans un café du centre historique du village, où se tenait un festival.Au total, 77 personnes ont été blessées, dont quatre gravement. Le cuisinier du café a su lancer l'alerte, ce qui a permis de limiter le nombre de victimes, a indiqué le bourgmestre Antonio Moreno Ferrer.", "external_links": [], "published": "2016-10-02T13:32:00.000+03:00", "crawled": "2016-10-02T08:45:00.790+03:00", "highlightTitle": ""}