{"organizations": [], "uuid": "8256d247cd2f02bf386b7dbd34d5b1a125c6038b", "thread": {"social": {"gplus": {"shares": 0}, "pinterest": {"shares": 0}, "vk": {"shares": 0}, "linkedin": {"shares": 0}, "facebook": {"likes": 0, "shares": 0, "comments": 0}, "stumbledupon": {"shares": 0}}, "site_full": "www.lequipe.fr", "main_image": "", "site_section": "http://www.lequipe.fr/Xml/actu_rss.xml", "section_title": "L'Equipe.fr Actu de tous les sports", "url": "http://www.lequipe.fr/Basket/Actualites/Grece-l-improbable-tir-au-buzzer-d-andreja-milutinovic/733317", "country": "FR", "domain_rank": 977, "title": "Basket - WTF - Grèce : L'improbable tir au buzzer d'Andreja Milutinovic", "performance_score": 0, "site": "lequipe.fr", "participants_count": 0, "title_full": "Basket - WTF - Grèce : L'improbable tir au buzzer d'Andreja Milutinovic", "spam_score": 0.0, "site_type": "news", "published": "2016-10-03T02:23:00.000+03:00", "replies_count": 0, "uuid": "8256d247cd2f02bf386b7dbd34d5b1a125c6038b"}, "author": "", "url": "http://www.lequipe.fr/Basket/Actualites/Grece-l-improbable-tir-au-buzzer-d-andreja-milutinovic/733317", "ord_in_thread": 0, "title": "Basket - WTF - Grèce : L'improbable tir au buzzer d'Andreja Milutinovic", "locations": [], "entities": {"persons": [], "locations": [], "organizations": []}, "highlightText": "", "language": "french", "persons": [], "text": "WTF Grèce : L'improbable tir au buzzer d'Andreja Milutinovic Le 02/10/2016 à 20:23:00 Le Serbe Andreja Milutinovic, pensionnaire du club de Koroivos, a inscrit un tir exceptionnel dimanche en Coupe de Grèce.   Placé un bon mètre derrière sa propre ligne de lancers-francs, Andreja Milutinovic a inscrit l'un des shoots de l'année, dimanche en Coup de Grèce. Au buzzer de la première mi-temps du duel face au Apollon Patras, le Serbe a en effet envoyé une prière à une main, laquelle a traversé tout le terrain et heurté la planche avant de faire mouche. Et son club, Koroivos, a même fini par s'imposer (88-82).", "external_links": [], "published": "2016-10-03T02:23:00.000+03:00", "crawled": "2016-10-02T21:48:07.859+03:00", "highlightTitle": ""}