{"organizations": [], "uuid": "1f4404be8accce7c489865977ccda0f519ada1fb", "thread": {"social": {"gplus": {"shares": 0}, "pinterest": {"shares": 0}, "vk": {"shares": 0}, "linkedin": {"shares": 0}, "facebook": {"likes": 0, "shares": 0, "comments": 0}, "stumbledupon": {"shares": 0}}, "site_full": "article.wn.com", "main_image": "//cdn0.wn.com/o25/ph/img/02/c1/df113e3c9cc82c015c48f7fd85bb-grande.jpg", "site_section": "http://rss.wn.com/french/top-stories", "section_title": "WN.com - Top French Stories", "url": "https://article.wn.com/view/2016/10/01/Hull_CityChelsea_02_Chelsea_se_redresse/", "country": "GB", "domain_rank": 5594, "title": "Hull City-Chelsea (0-2), Chelsea se redresse", "performance_score": 0, "site": "wn.com", "participants_count": 1, "title_full": "Hull City-Chelsea (0-2), Chelsea se redresse - Worldnews.com", "spam_score": 0.0, "site_type": "news", "published": "2016-10-01T03:00:00.000+03:00", "replies_count": 0, "uuid": "1f4404be8accce7c489865977ccda0f519ada1fb"}, "author": "wn.com", "url": "https://article.wn.com/view/2016/10/01/Hull_CityChelsea_02_Chelsea_se_redresse/", "ord_in_thread": 0, "title": "Hull City-Chelsea (0-2), Chelsea se redresse", "locations": [], "entities": {"persons": [], "locations": [], "organizations": []}, "highlightText": "", "language": "french", "persons": [], "text": "Après trois matches sans victoire en championnat, Chelsea a repris du poil de la bête ce samedi en revenant avec les trois points de son déplacement à Hull (2-0). ...", "external_links": [], "published": "2016-10-01T03:00:00.000+03:00", "crawled": "2016-10-01T23:05:30.429+03:00", "highlightTitle": ""}