{"organizations": [], "uuid": "71741a4564b85b0761d2cd942d50929509fc5701", "thread": {"social": {"gplus": {"shares": 0}, "pinterest": {"shares": 0}, "vk": {"shares": 0}, "linkedin": {"shares": 0}, "facebook": {"likes": 0, "shares": 0, "comments": 0}, "stumbledupon": {"shares": 0}}, "site_full": "www.footmercato.net", "main_image": "", "site_section": "http://footmercato.net//flux-rss", "section_title": "Foot Mercato : Info Transferts Football - Actu Foot Transfert", "url": "http://www.footmercato.net/breves/mu-mourinho-charge-un-de-ses-adjoints_187458", "country": "FR", "domain_rank": 6556, "title": "MU : Mourinho charge un de ses adjoints !", "performance_score": 0, "site": "footmercato.net", "participants_count": 1, "title_full": "MU : Mourinho charge un de ses adjoints !", "spam_score": 0.0, "site_type": "news", "published": "2016-09-30T16:41:00.000+03:00", "replies_count": 0, "uuid": "71741a4564b85b0761d2cd942d50929509fc5701"}, "author": "Alexis Cimolino", "url": "http://www.footmercato.net/breves/mu-mourinho-charge-un-de-ses-adjoints_187458", "ord_in_thread": 0, "title": "MU : Mourinho charge un de ses adjoints !", "locations": [], "entities": {"persons": [], "locations": [], "organizations": []}, "highlightText": "", "language": "french", "persons": [], "text": "Accueil > Flash Mercato > MU : Mourinho charge un de ses adjoints ! MU : Mourinho charge un de ses adjoints ! Publié le : Alexis Cimolino Suivre @AlexisCIMOLINO \nUn événement a retenu l’attention jeudi soir lors du match d’Europa League entre Manchester United et les Ukrainiens de Zorya Luhansk. A la mi-temps de la rencontre, José Mourinho est visiblement entré dans une colère noire contre l’un de ses adjoints, Giovanni Cerra, devant les caméra de BT Sport . En cause, de mauvaises consignes données à Paul Pogba, rapporte le Daily Mail . \n« Paul était un peu perdu avec tous ces changements et, évidemment, je veux que mes assistants prennent soin de tous les détails », a expliqué le Portugais après la rencontre. Pas sûr, pour autant, que la victoire (1-0) des Red Devils ait réussi à le calmer.", "external_links": [], "published": "2016-09-30T16:41:00.000+03:00", "crawled": "2016-10-01T05:07:41.119+03:00", "highlightTitle": ""}