{"organizations": [], "uuid": "9dbab1868ac5088cb7072fe0303935e97aa9fe83", "thread": {"social": {"gplus": {"shares": 0}, "pinterest": {"shares": 0}, "vk": {"shares": 0}, "linkedin": {"shares": 0}, "facebook": {"likes": 0, "shares": 0, "comments": 0}, "stumbledupon": {"shares": 0}}, "site_full": "fr.finance.yahoo.com", "main_image": "https://s.yimg.com/bt/api/res/1.2/sR3hBBbFkB6WQvFD4gkb8Q--/YXBwaWQ9eW5ld3NfbGVnbztpbD1wbGFuZTtxPTc1O3c9NjAw/http://globalfinance.zenfs.com/fr_FR/Finance/FR_AFTP_LATRIBUNE_LIVE_1/musee-des-tissus.jpg", "site_section": "https://fr.finance.yahoo.com/actualites/partenaire-latribune/?format=rss", "section_title": "Archives des articles La Tribune - Yahoo France Finance", "url": "https://fr.finance.yahoo.com/actualites/mus%C3%A9e-tissus-emmanuel-imberton-pr%C3%AAt-115418584.html", "country": "US", "domain_rank": 5, "title": "Musée des Tissus : Emmanuel Imberton prêt à fermer la structure", "performance_score": 0, "site": "yahoo.com", "participants_count": 0, "title_full": "Musée des Tissus : Emmanuel Imberton prêt à fermer la structure", "spam_score": 0.0, "site_type": "news", "published": "2016-10-03T19:54:00.000+03:00", "replies_count": 0, "uuid": "9dbab1868ac5088cb7072fe0303935e97aa9fe83"}, "author": "", "url": "https://fr.finance.yahoo.com/actualites/mus%C3%A9e-tissus-emmanuel-imberton-pr%C3%AAt-115418584.html", "ord_in_thread": 0, "title": "Musée des Tissus : Emmanuel Imberton prêt à fermer la structure", "locations": [], "entities": {"persons": [], "locations": [], "organizations": []}, "highlightText": "", "language": "french", "persons": [], "text": "Taxe sur les dividendes : Bercy contraint de sortir de l'impasse fiscale BFM Business - il y a 6 minutes Le gouvernement est contraint de proposer d'ici à la fin de 2016 un dispositif fiscal remplaçant la taxe à 3% sur les dividendes, retoquée vendredi 30 septembre 2016, par le Conseil constitutionnel. Elle avait rapporté près de 2,15 milliards d'euros … Suite » GB/Brexit:   13   31   31   42   18   37 minutes Les fuites fusent sur le Net à propos de la gamme de smartphones que Google présente mardi 4 octobre. Le géant du web est-il victime ou s'inspire-t-il de fuites savamment organisées à l'instar d'Apple pour ses iPhone? … Suite »", "external_links": [], "published": "2016-10-03T19:54:00.000+03:00", "crawled": "2016-10-03T15:22:20.977+03:00", "highlightTitle": ""}