{"organizations": [], "uuid": "201df8f6ca325510a4d31986868f1c3903aa2609", "thread": {"social": {"gplus": {"shares": 0}, "pinterest": {"shares": 0}, "vk": {"shares": 0}, "linkedin": {"shares": 0}, "facebook": {"likes": 0, "shares": 0, "comments": 0}, "stumbledupon": {"shares": 0}}, "site_full": "www.lavenir.net", "main_image": "http://s4.lavenircdn.net/Assets/Images_Upload/Actu24/2016/10/04/f7b7d82e-8a1d-11e6-98d7-3d46c8e02b91_original.jpg", "site_section": "http://www.lavenir.net/rss.aspx?foto=1&intro=1&section=info&info=8f8012c3-d2ca-4192-9ae8-fc61d77cb44d", "section_title": "L'Avenir.net: Le fil info", "url": "http://www.lavenir.net/cnt/dmf20161004_00890873", "country": "BE", "domain_rank": 8618, "title": "Le régime syrien progresse à Alep après des combats de rue", "performance_score": 0, "site": "lavenir.net", "participants_count": 0, "title_full": "Le régime syrien progresse à Alep après des combats de rue", "spam_score": 0.0, "site_type": "news", "published": "2016-10-04T18:34:00.000+03:00", "replies_count": 0, "uuid": "201df8f6ca325510a4d31986868f1c3903aa2609"}, "author": "", "url": "http://www.lavenir.net/cnt/dmf20161004_00890873", "ord_in_thread": 0, "title": "Le régime syrien progresse à Alep après des combats de rue", "locations": [], "entities": {"persons": [], "locations": [], "organizations": []}, "highlightText": "", "language": "french", "persons": [], "text": "- Belga Les ruines d’Alep, après un énième bombardement, théâtre de combats de rue.-AFP \nLes troupes du régime syrien progressaient mardi au cœur d’Alep après avoir repris aux rebelles plusieurs bâtiments lors d’intenses combats de rue, selon l’Observatoire syrien des droits de l’Homme (OSDH). \nLes forces gouvernementales se sont emparées d’immeubles stratégiques dans le quartier de Suleiman al-Halabi, dans le centre d’Alep, et progressaient vers d’autres zones rebelles plus au nord, selon l’Observatoire. «Les forces du régime avancent petit à petit dans le centre d’Alep et progresse plus au nord vers Boustane al-Bacha après des combats de rue aujourd’hui», a déclaré mardi le directeur de l’OSDH, Rami Abdel Rahmane. «Elles se concentrent sur les grands immeubles, qui servaient autrefois de bâtiments administratifs et d’où elles peuvent surveiller des quartiers entiers», a-t-il précisé. \nL’armée syrienne, soutenue par l’aviation russe, a lancé le 22 septembre une offensive militaire d’envergure pour reprendre la partie est d’Alep, contrôlée par les rebelles. \nDans le sud de la ville, le district de Cheikh Saïd a été la cible d’intenses raids du régime dans la nuit de lundi à mardi, selon un correspondant de l’AFP. Lundi, des bombardements sur Alep-Est ont tué 13 personnes, a rapporté l’OSDH. Notre Dossier Guerre en Syrie Les + lus", "external_links": [], "published": "2016-10-04T18:34:00.000+03:00", "crawled": "2016-10-04T13:46:56.053+03:00", "highlightTitle": ""}