{"organizations": [], "uuid": "decf4da15ca831d24eac1323b30736199e768344", "thread": {"social": {"gplus": {"shares": 0}, "pinterest": {"shares": 0}, "vk": {"shares": 0}, "linkedin": {"shares": 0}, "facebook": {"likes": 0, "shares": 0, "comments": 0}, "stumbledupon": {"shares": 0}}, "site_full": "fr.news.yahoo.com", "main_image": "", "site_section": "", "section_title": "", "url": "https://fr.news.yahoo.com/inde-cadavres-vaches-jonchent-toujours-101000424.html", "country": "US", "domain_rank": 5, "title": "En Inde, les cadavres de vaches jonchent toujours le sol", "performance_score": 0, "site": "yahoo.com", "participants_count": 0, "title_full": "En Inde, les cadavres de vaches jonchent toujours le sol", "spam_score": 0.2, "site_type": "news", "published": "2016-10-03T18:10:00.000+03:00", "replies_count": 0, "uuid": "decf4da15ca831d24eac1323b30736199e768344"}, "author": "", "url": "https://fr.news.yahoo.com/inde-cadavres-vaches-jonchent-toujours-101000424.html", "ord_in_thread": 0, "title": "En Inde, les cadavres de vaches jonchent toujours le sol", "locations": [], "entities": {"persons": [], "locations": [], "organizations": []}, "highlightText": "", "language": "french", "persons": [], "text": "Que sont-ils devenus : la tête à claques, Mickaël Vendetta, qui fête son anniversaire ? Télé-Loisirs.fr ", "external_links": [], "published": "2016-10-03T18:10:00.000+03:00", "crawled": "2016-10-03T13:48:45.658+03:00", "highlightTitle": ""}